liblincs.cpython-314-x86_64-linux-gnu.so
development/cycle.py
development/publish.py
doc-sources/conf.py
integration-tests/python-package-is-usable/test.py
lincs/__init__.py
lincs/__main__.py
lincs/classification.py
lincs/command_line_interface.py
lincs/description.py
lincs/liblincs_module_tests.py
lincs/visualization.py
lincs/liblincs/chrones.hpp
lincs/liblincs/classification.cpp
lincs/liblincs/classification.hpp
lincs/liblincs/generation.cpp
lincs/liblincs/generation.hpp
lincs/liblincs/internal.hpp
lincs/liblincs/io.cpp
lincs/liblincs/io.hpp
lincs/liblincs/learning.cpp
lincs/liblincs/learning.hpp
lincs/liblincs/lincs.hpp
lincs/liblincs/randomness-utils.cpp
lincs/liblincs/randomness-utils.hpp
lincs/liblincs/test-cuda-floating-points.cu
lincs/liblincs/unreachable.hpp
lincs/liblincs/variant-dispatch.hpp
lincs/liblincs/io/alternatives.cpp
lincs/liblincs/io/alternatives.hpp
lincs/liblincs/io/exception.cpp
lincs/liblincs/io/exception.hpp
lincs/liblincs/io/model.cpp
lincs/liblincs/io/model.hpp
lincs/liblincs/io/problem.cpp
lincs/liblincs/io/problem.hpp
lincs/liblincs/io/validation.cpp
lincs/liblincs/io/validation.hpp
lincs/liblincs/learning/exception.cpp
lincs/liblincs/learning/exception.hpp
lincs/liblincs/learning/mrsort-by-weights-profiles-breed.cpp
lincs/liblincs/learning/mrsort-by-weights-profiles-breed.hpp
lincs/liblincs/learning/pre-processing.cpp
lincs/liblincs/learning/pre-processing.hpp
lincs/liblincs/learning/ucncs-by-max-sat-by-coalitions.cpp
lincs/liblincs/learning/ucncs-by-max-sat-by-coalitions.hpp
lincs/liblincs/learning/ucncs-by-max-sat-by-separation.cpp
lincs/liblincs/learning/ucncs-by-max-sat-by-separation.hpp
lincs/liblincs/learning/ucncs-by-sat-by-coalitions.cpp
lincs/liblincs/learning/ucncs-by-sat-by-coalitions.hpp
lincs/liblincs/learning/ucncs-by-sat-by-separation.cpp
lincs/liblincs/learning/ucncs-by-sat-by-separation.hpp
lincs-2.0.2.dist-info/METADATA
lincs-2.0.2.dist-info/WHEEL
lincs-2.0.2.dist-info/entry_points.txt
lincs-2.0.2.dist-info/top_level.txt
lincs-2.0.2.dist-info/RECORD
lincs-2.0.2.dist-info/licenses/COPYING
lincs-2.0.2.dist-info/licenses/COPYING.LESSER
