Metadata-Version: 2.1
Name: lincs
Version: 2.0.2
Summary: Learn and Infer Non Compensatory Sortings
Home-page: https://github.com/MICS-Lab/lincs
Author: Vincent Jacques
Author-email: vincent@vincent-jacques.net
License: LGPLv3
Classifier: Development Status :: 5 - Production/Stable
Classifier: Environment :: Console
Classifier: Intended Audience :: Developers
Classifier: Intended Audience :: Science/Research
Classifier: License :: OSI Approved :: GNU Lesser General Public License v3 (LGPLv3)
Classifier: Operating System :: POSIX :: Linux
Classifier: Programming Language :: C++
Classifier: Programming Language :: Python :: 3 :: Only
Classifier: Topic :: Scientific/Engineering :: Artificial Intelligence
License-File: COPYING
License-File: COPYING.LESSER
Requires-Dist: click ~=8.1
Requires-Dist: matplotlib ~=3.7
Requires-Dist: six ~=1.16
